blendz/__init__.py
blendz/photoz.py
blendz/utilities.py
blendz/config/__init__.py
blendz/config/config.py
blendz/config/default_config.py
blendz/fluxes/__init__.py
blendz/fluxes/filters.py
blendz/fluxes/response.py
blendz/fluxes/templates.py
blendz/model/__init__.py
blendz/model/bpz.py
blendz/model/likelihood_only.py
blendz/model/model_base.py
blendz/photometry/__init__.py
blendz/photometry/galaxy.py
blendz/photometry/photometry.py
blendz/photometry/photometry_base.py
blendz/photometry/simulated_photometry.py
blendz/resources/config/defaultConfig.txt
blendz/resources/config/testComboConfig.txt
blendz/resources/config/testDataConfig.txt
blendz/resources/config/testListConfig.txt
blendz/resources/config/testRunConfig.txt
blendz/resources/data/bpz/UDFtest.cat
blendz/resources/filters/hst/F110W
blendz/resources/filters/hst/F160W
blendz/resources/filters/hst/F435W
blendz/resources/filters/hst/F606W
blendz/resources/filters/hst/F775W
blendz/resources/filters/hst/F850LP
blendz/resources/filters/lsst/g
blendz/resources/filters/lsst/i
blendz/resources/filters/lsst/r
blendz/resources/filters/lsst/u
blendz/resources/filters/lsst/y
blendz/resources/filters/lsst/z
blendz/resources/filters/sdss/g
blendz/resources/filters/sdss/i
blendz/resources/filters/sdss/r
blendz/resources/filters/sdss/u
blendz/resources/filters/sdss/z
blendz/resources/filters/viking/h
blendz/resources/filters/viking/j
blendz/resources/filters/viking/k
blendz/resources/filters/viking/y
blendz/resources/filters/viking/z
blendz/resources/templates/BPZ6
blendz/resources/templates/BPZ8
blendz/resources/templates/bpz/El_B2004a
blendz/resources/templates/bpz/Im_B2004a
blendz/resources/templates/bpz/SB2_B2004a
blendz/resources/templates/bpz/SB3_B2004a
blendz/resources/templates/bpz/Sbc_B2004a
blendz/resources/templates/bpz/Scd_B2004a
blendz/resources/templates/bpz/ssp_25Myr_z008
blendz/resources/templates/bpz/ssp_5Myr_z008
blendz-1.0.0.dist-info/DESCRIPTION.rst
blendz-1.0.0.dist-info/METADATA
blendz-1.0.0.dist-info/RECORD
blendz-1.0.0.dist-info/WHEEL
blendz-1.0.0.dist-info/metadata.json
blendz-1.0.0.dist-info/top_level.txt
