Metadata-Version: 2.0
Name: blendz
Version: 1.0.0
Summary: Bayesian photometric redshifts of blended sources.
Home-page: http://blendz.readthedocs.io
Author: Daniel Michael Jones
Author-email: d.jones15@imperial.ac.uk
License: MIT
Platform: UNKNOWN
Requires-Dist: numpy
Requires-Dist: scipy
Requires-Dist: tqdm
Requires-Dist: nestle
Requires-Dist: dill
Requires-Dist: future
Requires-Dist: emcee
